packageTopsis/__init__.py
packageTopsis/topsis.py
TOPSIS_YASHPAL_101803611-5.0.0.dist-info/License.txt
TOPSIS_YASHPAL_101803611-5.0.0.dist-info/METADATA
TOPSIS_YASHPAL_101803611-5.0.0.dist-info/WHEEL
TOPSIS_YASHPAL_101803611-5.0.0.dist-info/entry_points.txt
TOPSIS_YASHPAL_101803611-5.0.0.dist-info/top_level.txt
TOPSIS_YASHPAL_101803611-5.0.0.dist-info/RECORD
