Metadata-Version: 2.1
Name: TOPSIS-YASHPAL-101803611
Version: 5.0.0
Summary: A Python package implementing TOPSIS technique.
Home-page: UNKNOWN
Author: Yashpal
Author-email: yyashpal_be18@thapar.edu
License: MIT
Platform: UNKNOWN
Classifier: License :: OSI Approved :: MIT License
Classifier: Programming Language :: Python :: 3
Classifier: Programming Language :: Python :: 3.7
Requires-Dist: numpy
Requires-Dist: pandas
